clutch/__init__.py
clutch/client.py
clutch/py.typed
clutch/method/__init__.py
clutch/method/method.py
clutch/method/misc.py
clutch/method/queue.py
clutch/method/session.py
clutch/method/shared.py
clutch/method/torrent.py
clutch/network/__init__.py
clutch/network/connection.py
clutch/network/session.py
clutch/network/utility.py
clutch/network/rpc/__init__.py
clutch/network/rpc/convert.py
clutch/network/rpc/message.py
clutch/schema/__init__.py
clutch/schema/request/__init__.py
clutch/schema/request/misc/__init__.py
clutch/schema/request/misc/bandwidth_group.py
clutch/schema/request/misc/port_test.py
clutch/schema/request/session/__init__.py
clutch/schema/request/session/accessor.py
clutch/schema/request/session/mutator.py
clutch/schema/request/session/shared.py
clutch/schema/request/torrent/__init__.py
clutch/schema/request/torrent/accessor.py
clutch/schema/request/torrent/add.py
clutch/schema/request/torrent/mutator.py
clutch/schema/user/__init__.py
clutch/schema/user/method/__init__.py
clutch/schema/user/method/misc.py
clutch/schema/user/method/shared.py
clutch/schema/user/method/session/__init__.py
clutch/schema/user/method/session/accessor.py
clutch/schema/user/method/session/mutator.py
clutch/schema/user/method/session/shared.py
clutch/schema/user/method/torrent/__init__.py
clutch/schema/user/method/torrent/accessor.py
clutch/schema/user/method/torrent/action.py
clutch/schema/user/method/torrent/add.py
clutch/schema/user/method/torrent/move.py
clutch/schema/user/method/torrent/mutator.py
clutch/schema/user/method/torrent/remove.py
clutch/schema/user/method/torrent/rename.py
clutch/schema/user/response/__init__.py
clutch/schema/user/response/misc.py
clutch/schema/user/response/session/__init__.py
clutch/schema/user/response/session/accessor.py
clutch/schema/user/response/session/stats.py
clutch/schema/user/response/torrent/__init__.py
clutch/schema/user/response/torrent/accessor.py
clutch/schema/user/response/torrent/add.py
transmission_clutch-7.0.3.dist-info/METADATA
transmission_clutch-7.0.3.dist-info/WHEEL
transmission_clutch-7.0.3.dist-info/licenses/LICENSE
transmission_clutch-7.0.3.dist-info/RECORD
