Metadata-Version: 2.4
Name: transmission-clutch
Version: 7.0.3
Summary: An RPC client library for the Transmission BitTorrent client
Project-URL: Documentation, https://clutch.readthedocs.io/en/latest/
Project-URL: Repository, https://github.com/mhadam/clutch
Project-URL: Issues, https://github.com/mhadam/clutch/issues
Author-email: Michael Hadam <michael@hadam.us>
Maintainer-email: Michael Hadam <michael@hadam.us>
License-Expression: MIT
License-File: LICENSE
Requires-Python: >=3.10
Requires-Dist: pydantic~=2.10
Requires-Dist: requests~=2.32
